README.md
setup.py
as_a_service/__init__.py
as_a_service.egg-info/PKG-INFO
as_a_service.egg-info/SOURCES.txt
as_a_service.egg-info/dependency_links.txt
as_a_service.egg-info/top_level.txt