Metadata-Version: 1.1
Name: as-a-service
Version: 1.0.3
Summary: a simple tool to turn your function into a background service
Home-page: https://github.com/justheuristic/as_a_service
Author: UNKNOWN
Author-email: justheuristic@gmail.com
License: MIT
Keywords: service,background service,batched executor,parallel executor,background executor,background,deep learning,reinforcement learning
Platform: UNKNOWN
Classifier: Development Status :: 5 - Production/Stable
Classifier: Intended Audience :: Science/Research
Classifier: Intended Audience :: Developers
Classifier: Topic :: Scientific/Engineering
Classifier: License :: OSI Approved :: MIT License
Classifier: Programming Language :: Python :: 2.7 
Classifier: Programming Language :: Python :: 3.4 
Classifier: Programming Language :: Python :: 3.5 
Classifier: Programming Language :: Python :: 3.6 
Classifier: Programming Language :: Python :: 3.7 
